odoo9_addon_website_livechat_firstname-9.0.1.0.0-py2.7-nspkg.pth
odoo_addons/website_livechat_firstname/__openerp__.py
odoo_addons/website_livechat_firstname/__init__.py
odoo_addons/website_livechat_firstname/README.rst
odoo_addons/website_livechat_firstname/models/__init__.py
odoo_addons/website_livechat_firstname/models/mail_channel.py
odoo_addons/website_livechat_firstname/views/website_livechat_firstname_view.xml
odoo_addons/website_livechat_firstname/tests/__init__.py
odoo_addons/website_livechat_firstname/tests/test_mail_channel.py
odoo_addons/website_livechat_firstname/demo/res_partner_demo.xml
odoo_addons/website_livechat_firstname/static/description/icon.png
odoo9_addon_website_livechat_firstname-9.0.1.0.0.dist-info/top_level.txt
odoo9_addon_website_livechat_firstname-9.0.1.0.0.dist-info/WHEEL
odoo9_addon_website_livechat_firstname-9.0.1.0.0.dist-info/RECORD
odoo9_addon_website_livechat_firstname-9.0.1.0.0.dist-info/metadata.json
odoo9_addon_website_livechat_firstname-9.0.1.0.0.dist-info/DESCRIPTION.rst
odoo9_addon_website_livechat_firstname-9.0.1.0.0.dist-info/METADATA
odoo9_addon_website_livechat_firstname-9.0.1.0.0.dist-info/namespace_packages.txt
