Metadata-Version: 2.0
Name: odoo9-addon-website-livechat-firstname
Version: 9.0.1.0.0
Summary: Shows only the first name of the operator in the website
Home-page: https://github.com/OCA/social
Author: SMDrugstore, LasLabs, Odoo Community Association (OCA)
Author-email: support@odoo-community.org
License: LGPL-3
Platform: UNKNOWN
Requires-Dist: odoo (<9.1a,>=9.0a)
Requires-Dist: odoo9-addon-partner-firstname
Classifier: Programming Language :: Python :: 2.7
Classifier: Framework :: Odoo
Classifier: License :: OSI Approved :: GNU Lesser General Public License v3 (LGPLv3)
